Metadata-Version: 2.1
Name: sintaxis
Version: 0.0.4
Summary: Sintaxis es un comando line interface (CLI) que permite crear y testear ejercicios de programación.
Home-page: https://github.com/12aptor
Author: Paolo Soncco
Author-email: paolosonccodev@gmail.com
License: Apache License 2.0
Requires-Dist: colorama
Requires-Dist: python-socketio[asyncio_client]
